MovieChat/__init__.py
MovieChat/common/__init__.py
MovieChat/common/config.py
MovieChat/common/dist_utils.py
MovieChat/common/gradcam.py
MovieChat/common/logger.py
MovieChat/common/optims.py
MovieChat/common/registry.py
MovieChat/common/utils.py
MovieChat/conversation/__init__.py
MovieChat/conversation/conversation_video.py
MovieChat/datasets/__init__.py
MovieChat/datasets/data_utils.py
MovieChat/datasets/builders/__init__.py
MovieChat/datasets/builders/base_dataset_builder.py
MovieChat/datasets/builders/image_text_pair_builder.py
MovieChat/datasets/builders/instruct_builder.py
MovieChat/datasets/builders/video_caption_builder.py
MovieChat/datasets/datasets/__init__.py
MovieChat/datasets/datasets/base_dataset.py
MovieChat/datasets/datasets/caption_datasets.py
MovieChat/datasets/datasets/cc_sbu_dataset.py
MovieChat/datasets/datasets/dataloader_utils.py
MovieChat/datasets/datasets/laion_dataset.py
MovieChat/datasets/datasets/llava_instruct_dataset.py
MovieChat/datasets/datasets/video_instruct_dataset.py
MovieChat/datasets/datasets/webvid_datasets.py
MovieChat/models/Qformer.py
MovieChat/models/__init__.py
MovieChat/models/base_model.py
MovieChat/models/blip2.py
MovieChat/models/blip2_outputs.py
MovieChat/models/chat_model.py
MovieChat/models/eva_vit.py
MovieChat/models/eva_vit_with_tome.py
MovieChat/models/helpers.py
MovieChat/models/modeling_llama.py
MovieChat/models/moviechat.py
MovieChat/models/multimodal_preprocessors.py
MovieChat/models/process_video_data.py
MovieChat/processors/__init__.py
MovieChat/processors/base_processor.py
MovieChat/processors/blip_processors.py
MovieChat/processors/functional_video.py
MovieChat/processors/randaugment.py
MovieChat/processors/transforms_video.py
MovieChat/processors/video_processor.py
MovieChat/runners/__init__.py
MovieChat/runners/runner_base.py
MovieChat/runners/test.py
MovieChat/tasks/__init__.py
MovieChat/tasks/base_task.py
MovieChat/tasks/image_text_pretrain.py
MovieChat/tasks/video_text_pretrain.py
moviechat-0.6.3.dist-info/LICENSE
moviechat-0.6.3.dist-info/METADATA
moviechat-0.6.3.dist-info/WHEEL
moviechat-0.6.3.dist-info/top_level.txt
moviechat-0.6.3.dist-info/RECORD
