Metadata-Version: 2.1
Name: moviechat
Version: 0.6.3
Summary: Long video understanding
Author-email: Enxin Song <enxin.song.dut@gmail.com>
License: MIT License
Project-URL: homepage, https://rese1f.github.io/MovieChat/
Project-URL: repository, https://github.com/rese1f/MovieChat
Requires-Python: >=3.7
License-File: LICENSE
Requires-Dist: pip >=23.1.2
Requires-Dist: torch ==2.0.1
Requires-Dist: torchaudio ==2.0.2
Requires-Dist: torchvision ==0.15.2
Requires-Dist: accelerate ==0.16.0
Requires-Dist: aiohttp ==3.8.4
Requires-Dist: aiosignal ==1.3.1
Requires-Dist: async-timeout ==4.0.2
Requires-Dist: attrs ==22.2.0
Requires-Dist: bitsandbytes ==0.37.0
Requires-Dist: cchardet ==2.1.7
Requires-Dist: chardet ==5.1.0
Requires-Dist: contourpy ==1.0.7
Requires-Dist: cycler ==0.11.0
Requires-Dist: filelock ==3.9.0
Requires-Dist: fonttools ==4.38.0
Requires-Dist: frozenlist ==1.3.3
Requires-Dist: huggingface-hub ==0.13.4
Requires-Dist: importlib-resources ==5.12.0
Requires-Dist: kiwisolver ==1.4.4
Requires-Dist: matplotlib ==3.7.0
Requires-Dist: multidict ==6.0.4
Requires-Dist: openai ==0.27.0
Requires-Dist: packaging ==23.0
Requires-Dist: psutil ==5.9.4
Requires-Dist: pyparsing ==3.0.9
Requires-Dist: python-dateutil ==2.8.2
Requires-Dist: pyyaml ==6.0
Requires-Dist: regex ==2022.10.31
Requires-Dist: tokenizers ==0.13.2
Requires-Dist: tqdm ==4.64.1
Requires-Dist: transformers ==4.28.0
Requires-Dist: timm ==0.6.13
Requires-Dist: spacy ==3.5.1
Requires-Dist: webdataset ==0.2.48
Requires-Dist: scikit-learn ==1.2.2
Requires-Dist: scipy ==1.10.1
Requires-Dist: yarl ==1.8.2
Requires-Dist: zipp ==3.14.0
Requires-Dist: omegaconf ==2.3.0
Requires-Dist: opencv-python ==4.7.0.72
Requires-Dist: iopath ==0.1.10
Requires-Dist: decord ==0.6.0
Requires-Dist: tenacity ==8.2.2
Requires-Dist: einops ==0.6.1
Requires-Dist: SentencePiece ==0.1.99
Requires-Dist: ftfy ==6.1.1
Requires-Dist: pytorchvideo ==0.1.5
Requires-Dist: GPUtil ==1.4.0
Requires-Dist: moviepy ==1.0.3
Requires-Dist: scikit-image ==0.21.0
Requires-Dist: pytorch-mutex ==1.0 ; extra == "cuda"
